date_time/__init__.py
date_time/config.ini
date_time/listdir.py
date_time_pkg-0.0.4.dist-info/LICENSE
date_time_pkg-0.0.4.dist-info/METADATA
date_time_pkg-0.0.4.dist-info/WHEEL
date_time_pkg-0.0.4.dist-info/top_level.txt
date_time_pkg-0.0.4.dist-info/RECORD
