Metadata-Version: 2.1
Name: date-time-pkg
Version: 0.0.4
Summary: Contains a date and time generator
Home-page: https://github.com/mitchainslieg/listdir
Author: Mitch Ainslie
Author-email: mitch.ainslie.it@gmail.com
License: UNKNOWN
Platform: UNKNOWN
Classifier: Programming Language :: Python :: 3
Classifier: License :: OSI Approved :: MIT License
Classifier: Operating System :: OS Independent
